LICENSE.txt
MANIFEST.in
README.md
setup.cfg
setup.py
pbxonline/__init__.py
pbxonline/api.py
pbxonline/auth_handler.py
pbxonline/cache_handler.py
pbxonline/config.py
pbxonline/utils.py
pbxonline/cache/__init__.py
pbxonline/constants/__init__.py
pbxonline/constants/constants.py
pbxonline/constants/errors.py
pbxonline/endpoints/__init__.py
pbxonline/endpoints/action.py
pbxonline/endpoints/base.py
pbxonline/endpoints/pbx.py
pbxonline/models/__init__.py
pbxonline/models/base.py
pbxonline/models/errors.py
pbxonline/models/utils.py
python_pbxonline.egg-info/PKG-INFO
python_pbxonline.egg-info/SOURCES.txt
python_pbxonline.egg-info/dependency_links.txt
python_pbxonline.egg-info/requires.txt
python_pbxonline.egg-info/top_level.txt
tests/test_action.py
tests/test_auth.py
tests/test_endcall.py
tests/test_pbx.py
tests/test_startcall.py